peazip_wrapper/__init__.py
peazip_wrapper/peazip_wrapper.py
pzarchivator-0.1.dist-info/METADATA
pzarchivator-0.1.dist-info/WHEEL
pzarchivator-0.1.dist-info/top_level.txt
pzarchivator-0.1.dist-info/RECORD
