Metadata-Version: 2.1
Name: pzarchivator
Version: 0.1
Summary: Wrapper for PeaZip Command Line
